.gitignore
.gitlab-ci.yml
AUTHORS.md
CHANGELOG.md
CONTRIBUTING.md
LICENSE.md
README.md
RELEASING.md
install.ps1
install.sh
mkdocs.yml
pyproject.toml
requirements.txt
setup.cfg
setup.py
docs/development.md
docs/index.md
docs/install.md
docs/users.md
docs/img/curved_lane.png
docs/img/lanes.png
docs/img/measurement_lanes.png
docs/img/projects.png
docs/img/types_and_edit_mode.png
iocbio/__init__.py
iocbio.gel.egg-info/PKG-INFO
iocbio.gel.egg-info/SOURCES.txt
iocbio.gel.egg-info/dependency_links.txt
iocbio.gel.egg-info/entry_points.txt
iocbio.gel.egg-info/requires.txt
iocbio.gel.egg-info/top_level.txt
iocbio/gel/__init__.py
iocbio/gel/app.py
iocbio/gel/const.py
iocbio/gel/logging.ini
iocbio/gel/application/__init__.py
iocbio/gel/application/container.py
iocbio/gel/application/event_consumer.py
iocbio/gel/application/event_registry.py
iocbio/gel/application/file_digest.py
iocbio/gel/application/number_list.py
iocbio/gel/application/settings_proxy.py
iocbio/gel/application/application_state/__init__.py
iocbio/gel/application/application_state/context.py
iocbio/gel/application/application_state/mode.py
iocbio/gel/application/application_state/state.py
iocbio/gel/application/image/__init__.py
iocbio/gel/application/image/background_method.py
iocbio/gel/application/image/image.py
iocbio/gel/application/image/image_source.py
iocbio/gel/application/image/image_source_setup.py
iocbio/gel/application/image/image_state.py
iocbio/gel/application/image/omero_client.py
iocbio/gel/application/image/processing_cache.py
iocbio/gel/application/image/region.py
iocbio/gel/application/image/repository_backend.py
iocbio/gel/application/image/repository_backend_local.py
iocbio/gel/application/image/repository_backend_omero.py
iocbio/gel/application/thread/__init__.py
iocbio/gel/application/thread/cache_operations.py
iocbio/gel/application/thread/fetch_image_from_omero.py
iocbio/gel/application/thread/job.py
iocbio/gel/application/thread/load_image_preview.py
iocbio/gel/application/thread/pool_worker.py
iocbio/gel/application/thread/rolling_ball.py
iocbio/gel/application/thread/sequential_worker.py
iocbio/gel/application/thread/thread_pool.py
iocbio/gel/application/thread/worker.py
