Metadata-Version: 2.4
Name: iocbio.gel
Version: 1.1.0
Summary: IOCBio Gel
Home-page: https://iocbio.gitlab.io/gel
Author: IOCBio team
Author-email: iocbio@sysbio.ioc.ee
License: GPLv3
Classifier: Development Status :: 5 - Production/Stable
Classifier: Intended Audience :: Science/Research
Classifier: License :: OSI Approved :: GNU General Public License v3 or later (GPLv3+)
Classifier: Programming Language :: Python :: 3
Classifier: Topic :: Scientific/Engineering
License-File: LICENSE.md
License-File: AUTHORS.md
Requires-Dist: sqlalchemy~=1.4.46
Requires-Dist: PySide6~=6.9
Requires-Dist: dependency_injector
Requires-Dist: scikit-image~=0.24.0
Requires-Dist: qimage2ndarray~=1.10.0
Requires-Dist: zeroc-ice
Requires-Dist: omero-py~=5.13.1
Requires-Dist: alembic~=1.8.1
Requires-Dist: pyqtgraph~=0.13.7
Requires-Dist: shiboken6~=6.9
Requires-Dist: psycopg2-binary
Requires-Dist: keyring
Requires-Dist: sqlparse~=0.4.3
Requires-Dist: XlsxWriter~=3.0.8
Dynamic: author
Dynamic: author-email
Dynamic: classifier
Dynamic: description
Dynamic: description-content-type
Dynamic: home-page
Dynamic: license
Dynamic: license-file
Dynamic: requires-dist
Dynamic: summary
